MANIFEST.in
VERSION
distribute_setup.py
setup.py
lib/logbook_zmqpush.py
lib/logbook_zmqpush.egg-info/PKG-INFO
lib/logbook_zmqpush.egg-info/SOURCES.txt
lib/logbook_zmqpush.egg-info/dependency_links.txt
lib/logbook_zmqpush.egg-info/requires.txt
lib/logbook_zmqpush.egg-info/top_level.txt