Metadata-Version: 1.0
Name: logbook-zmqpush
Version: 0.2.0
Summary: ZMQ_PUSH-based handler for Logbook
Home-page: http://github.com/zacharyvoase/logbook-zmqpush
Author: Zachary Voase
Author-email: z@zacharyvoase.com
License: UNKNOWN
Platform: UNKNOWN
